{
  "id": "samenwerken",
  "title": "Samen onderzoeken",
  "cover": "voorkant.svg",
  "viewerTemplate": "classic",
  "cssVars": {
    "--pk-set-accent": "#F3D7A3",
    "--pk-set-bg": "#FFFFFF",
    "--pk-set-card": "rgba(255,255,255,1)"
  },
  "backMode": "mirror",
  "ui": {
    "menu": {
      "showInfo": true,
      "showShuffle": true,
      "showAllSets": true
    },
    "sheet": {
      "enabled": true,
      "defaultMode": "cards"
    },
    "index": {
      "layout": "hero-grid",
      "background": {
        "palette": [
          "#F3D7A3"
        ]
      }
    },
    "themeCss": "theme.css",
    "cardModes": {},
    "cardShapes": {
      "cover": [],
      "verkennen": [],
      "duiden": [],
      "verbinden": [],
      "verhelderen": [],
      "vertragen": [],
      "bewegen": []
    },
    "coverTexts": [
      {
        "text": "Samen onderzoeken",
        "x": 12,
        "y": 24,
        "valign": "top",
        "size": 18,
        "align": "left",
        "weight": "regular",
        "italic": false,
        "underline": false,
        "font": "IBM Plex Sans",
        "color": "#1a1a2e",
        "bg": ""
      },
      {
        "text": "",
        "x": 12,
        "y": 50,
        "valign": "center",
        "size": 14,
        "align": "left",
        "weight": "regular",
        "italic": false,
        "underline": false,
        "font": "IBM Plex Sans",
        "color": "#1a1a2e",
        "bg": ""
      }
    ]
  },
  "themes": [
    {
      "key": "verkennen",
      "label": "Verkennen",
      "card": "verkennen.svg"
    },
    {
      "key": "duiden",
      "label": "Duiden",
      "card": "duiden.svg"
    },
    {
      "key": "verbinden",
      "label": "Verbinden",
      "card": "verbinden.svg"
    },
    {
      "key": "verhelderen",
      "label": "Verhelderen",
      "card": "verhelderen.svg"
    },
    {
      "key": "vertragen",
      "label": "Vertragen",
      "card": "vertragen.svg"
    },
    {
      "key": "bewegen",
      "label": "Bewegen",
      "card": "bewegen.svg"
    }
  ]
}